MANIFEST.in
setup.cfg
setup.py
pydawn/__init__.py
pydawn/adb_util.py
pydawn/browser_utils.py
pydawn/bsddb_utils.py
pydawn/burst_detect.py
pydawn/calc_distance.py
pydawn/cmd_utils.py
pydawn/co_occurrence.py
pydawn/command.py
pydawn/compare_distance.py
pydawn/exception_utils.py
pydawn/file_lock.py
pydawn/file_utils.py
pydawn/img_utils.py
pydawn/location_utils.py
pydawn/network_utils.py
pydawn/secure_utils.py
pydawn/simple_spider.py
pydawn/sqlite_utils.py
pydawn/string_utils.py
pydawn/test.py
pydawn/time_utils.py
pydawn/xpath_utils.py
pydawn.egg-info/PKG-INFO
pydawn.egg-info/SOURCES.txt
pydawn.egg-info/dependency_links.txt
pydawn.egg-info/entry_points.txt
pydawn.egg-info/requires.txt
pydawn.egg-info/top_level.txt
pydawn.egg-info/zip-safe