Metadata-Version: 1.0
Name: pydawn
Version: 1.0.22
Summary: some useful tool
Home-page: UNKNOWN
Author: palydawn
Author-email: palydawn@163.com
License: UNKNOWN
Keywords: palydawn
Platform: UNKNOWN
